LICENSE
mhdscraper/__init__.py
mhdscraper/mhdscraper.py
mhdscraper-1.0.3.dist-info/LICENSE
mhdscraper-1.0.3.dist-info/WHEEL
mhdscraper-1.0.3.dist-info/METADATA
mhdscraper-1.0.3.dist-info/RECORD
