Metadata-Version: 2.1
Name: mhdscraper
Version: 1.0.3
Summary: Mediawiki history dumps scraper, a module that scrapes the site of "Mediawiki history dumps" and returns to you the available content.
Home-page: https://github.com/euberdeveloper/wikimedia-history-dumps-scraper#pip
License: ISC
Keywords: mediawiki,mediawiki-history-dumps,tsv,scraper,wikipedia,wikimedia
Author: Eugenio Berretta
Author-email: euberdeveloper@gmail.com
Requires-Python: >=3.9,<4.0
Classifier: License :: OSI Approved
Classifier: Programming Language :: Python :: 3
Classifier: Programming Language :: Python :: 3.9
Requires-Dist: requests (>=2.25.1,<3.0.0)
Project-URL: Repository, https://github.com/euberdeveloper/wikimedia-history-dumps-scraper#pip
